csonh.py
csonh-1.0.1.post1.dist-info/licenses/LICENSE
csonh-1.0.1.post1.dist-info/METADATA
csonh-1.0.1.post1.dist-info/WHEEL
csonh-1.0.1.post1.dist-info/top_level.txt
csonh-1.0.1.post1.dist-info/RECORD
