Metadata-Version: 2.4
Name: csonh
Version: 1.0.1.post1
Summary: CSONH - Concise Structured Object Notation for Humanity
Author-email: Michael Goldman <mike.goldman@allstreets.org>
License: MIT License
Project-URL: Homepage, https://github.com/pythagorean/csonh
Project-URL: Issues, https://github.com/pythagorean/csonh/issues
Keywords: cson,json,parser,config,strict
Classifier: Programming Language :: Python :: 3
Classifier: License :: OSI Approved :: MIT License
Classifier: Operating System :: OS Independent
Classifier: Topic :: Software Development :: Libraries :: Python Modules
Classifier: Topic :: Text Processing :: Markup
Requires-Python: >=3.7
License-File: LICENSE
Dynamic: license-file
